psplib/ProjectInstance.py
psplib/__init__.py
psplib/parse.py
psplib/parse_aslib.py
psplib/parse_mplib.py
psplib/parse_patterson.py
psplib/parse_psplib.py
psplib/parse_rcpsp_max.py
psplib/parse_rcpsp_ps.py
psplib-0.3.0.dist-info/METADATA
psplib-0.3.0.dist-info/WHEEL
psplib-0.3.0.dist-info/licenses/LICENSE.md
psplib-0.3.0.dist-info/RECORD
