Metadata-Version: 2.4
Name: psplib
Version: 0.3.0
Summary: A parser for project scheduling instances.
Project-URL: Repository, https://github.com/PyJobShop/PSPLIB
Author-email: Leon Lan <l.lan@vu.nl>
License: MIT License
License-File: LICENSE.md
Keywords: project scheduling,psplib,scheduling
Classifier: Development Status :: 5 - Production/Stable
Classifier: Intended Audience :: Developers
Classifier: Intended Audience :: Science/Research
Classifier: License :: OSI Approved :: MIT License
Classifier: Programming Language :: Python :: 3
Classifier: Topic :: Scientific/Engineering
Classifier: Topic :: Software Development
Requires-Python: >=3.9
